easytreevis/__init__.py
easytreevis/core.py
easytreevis/layout.py
easytreevis/render.py
easytreevis/utils.py
easytreevis-1.0.0.dist-info/licenses/LICENSE
easytreevis-1.0.0.dist-info/METADATA
easytreevis-1.0.0.dist-info/WHEEL
easytreevis-1.0.0.dist-info/top_level.txt
easytreevis-1.0.0.dist-info/RECORD
