Metadata-Version: 2.4
Name: easytreevis
Version: 1.0.0
Summary: Package for easy visualisation of trees in Python
Author-email: Michał Gomułczak <michal.gomulczak1@gmail.com>
License: MIT License
License-File: LICENSE
Requires-Dist: svgwrite>=1.4.3
Dynamic: license-file
